{"name":"Brave New World","description":"Do this first. choose your class and complete your first quest!","quests":[{"uuid":"de9ab58f-24cb-4dc4-b187-510ad26b991c","name":"Chef","description":"The chef loves to cook his foes. simply roast them to win.","x":22,"y":194,"icon":{"id":"harvestcraft:hamandpineapplepizzaitem"},"prerequisites":["a99d52d9-1a7c-48bf-8e53-8c4c4e89175d"],"optionlinks":["65267e6c-4292-4147-ab5c-c9f8bc7826a7","6500fa68-f244-4c49-8726-1cad72c4d308","771e243c-7002-4848-a37a-332a5f9a6257","503079c8-2c3f-4951-af63-767092982afd","a99d52d9-1a7c-48bf-8e53-8c4c4e89175d","42d26513-56ec-4340-8dcc-c3f2a2bc07a7","b810069b-1af2-41de-bcea-2b084d2b3604","a8f25ab0-5f32-4971-a7ab-5c40757fe96e"],"reward":[{"id":"minecraft:leather_boots","nbt":"{RepairCost:0,display:{color:16383998,Name:\"Chefs shoes\"}}"},{"id":"harvestcraft:pumpkincheesecakeitem","amount":5},{"id":"minecraft:leather_chestplate","nbt":"{RepairCost:0,display:{color:16383998,Name:\"Chefs apron\"}}"},{"id":"littlelooter:machete","nbt":"{RepairCost:0,display:{Name:\"Chefs knife\"}}"},{"id":"harvestcraft:extremechiliitem","amount":5},{"id":"harvestcraft:coconutshrimpitem","amount":5},{"id":"minecraft:furnace","nbt":"{RepairCost:0,display:{Name:\"Chefs oven\"}}"}],"commandrewards":[]},{"uuid":"65267e6c-4292-4147-ab5c-c9f8bc7826a7","name":"Cheeki Breeki","description":"Cheeki breeki i\u0027ve danke","x":144,"y":73,"icon":{"id":"mw:ak47"},"prerequisites":["e2d1d48e-bfa1-47d0-b196-bdc29db11d54"],"reward":[{"id":"mw:makarovpm"},{"id":"mw:magazine9mm","amount":3,"nbt":"{Ammo:10,Instance:[B;69B,19B,-30B,-10B,85B,-125B,88B,5B,15B,5B,5B,57B,-117B,82B,-117B,-88B,0B,0B,0B,0B,48B,44B,-127B,-118B,-4B,100B,65B,-98B,-114B,-126B,-95B,80B,-98B,101B,88B,-21B,0B,0B,27B,97B,0B,0B,0B,4B,0B,0B,0B,0B,0B,0B,0B,4B,-25B,70B,62B,-7B,-42B,-85B,-70B,58B,54B,-123B,77B,22B,4B,-113B,122B,14B,0B,0B,0B,0B,0B,0B,0B,0B,0B,0B,0B,0B,0B,0B,0B,0B,0B,0B,0B,0B,0B,0B,0B,0B,0B,0B,0B,0B,0B,0B,0B,0B,0B,0B,0B,0B,0B,0B,0B,0B,0B,0B,0B,0B,0B,0B,0B,0B,0B,0B,0B,0B,0B,0B,0B,0B,0B,0B,0B,0B,0B,0B,0B,0B,0B,0B,0B,0B,0B,0B,0B,0B,0B,0B,0B,0B,0B,0B,0B,0B,0B,0B,0B,0B,0B,0B,0B,0B,0B,0B,0B,0B,0B,0B,0B,0B,0B,0B,0B,0B,0B,0B,0B,0B,0B,0B,0B,0B,0B,0B,0B,0B,0B,0B,0B,0B,0B,0B,0B,0B,0B,0B,0B,0B,0B,0B,0B,0B,0B,0B,0B,0B,0B,0B,0B,0B,0B,0B,0B,0B,0B,0B,0B,0B,0B,0B,0B,0B,0B,0B,0B,0B,0B,0B,0B,0B,0B,0B,0B,0B,0B,0B,0B,0B,0B,0B,0B,0B,0B,0B,0B,0B,0B,0B,0B,0B,0B,0B,0B,0B,0B,0B,0B,0B,0B,0B,0B,0B]}"}],"commandrewards":[]},{"uuid":"6500fa68-f244-4c49-8726-1cad72c4d308","name":"Medic","description":"The medic is just here to help.","x":129,"y":191,"icon":{"id":"roughtweaks:medikit"},"prerequisites":["e2d1d48e-bfa1-47d0-b196-bdc29db11d54"],"reward":[{"id":"roughtweaks:medikit","amount":15},{"id":"roughtweaks:medikitenchanted","amount":5},{"id":"littlelooter:tape","amount":5},{"id":"minecraft:leather_boots","nbt":"{display:{color:11546150}}"},{"id":"minecraft:leather_helmet","nbt":"{display:{color:11546150}}"}],"commandrewards":[]},{"uuid":"771e243c-7002-4848-a37a-332a5f9a6257","name":"Merica","description":"His freedom is unmatched.","x":144,"y":44,"icon":{"id":"mw:m416"},"prerequisites":["e2d1d48e-bfa1-47d0-b196-bdc29db11d54"],"reward":[{"id":"mw:m9berettamag","amount":2,"nbt":"{Ammo:15,Instance:[B;69B,19B,-30B,-10B,85B,-125B,88B,5B,15B,5B,5B,57B,-117B,82B,-117B,-88B,0B,0B,0B,0B,105B,-65B,-88B,-3B,-118B,73B,70B,75B,-122B,16B,63B,-23B,127B,-16B,-62B,91B,0B,0B,27B,95B,0B,0B,0B,1B,0B,0B,0B,0B,0B,0B,0B,1B,-25B,70B,62B,-7B,-42B,-85B,-70B,58B,54B,-123B,77B,22B,4B,-113B,122B,14B,0B,0B,0B,0B,0B,0B,0B,0B,0B,0B,0B,0B,0B,0B,0B,0B,0B,0B,0B,0B,0B,0B,0B,0B,0B,0B,0B,0B,0B,0B,0B,0B,0B,0B,0B,0B,0B,0B,0B,0B,0B,0B,0B,0B,0B,0B,0B,0B,0B,0B,0B,0B,0B,0B,0B,0B,0B,0B,0B,0B,0B,0B,0B,0B,0B,0B,0B,0B,0B,0B,0B,0B,0B,0B,0B,0B,0B,0B,0B,0B,0B,0B,0B,0B,0B,0B,0B,0B,0B,0B,0B,0B,0B,0B,0B,0B,0B,0B,0B,0B,0B,0B,0B,0B,0B,0B,0B,0B,0B,0B,0B,0B,0B,0B,0B,0B,0B,0B,0B,0B,0B,0B,0B,0B,0B,0B,0B,0B,0B,0B,0B,0B,0B,0B,0B,0B,0B,0B,0B,0B,0B,0B,0B,0B,0B,0B,0B,0B,0B,0B,0B,0B,0B,0B,0B,0B,0B,0B,0B,0B,0B,0B,0B,0B,0B,0B,0B,0B,0B,0B,0B,0B,0B,0B,0B,0B,0B,0B,0B,0B,0B,0B,0B,0B,0B,0B,0B,0B]}"},{"id":"mw:m9","nbt":"{Instance:[B;-32B,83B,21B,-112B,-126B,43B,-31B,45B,117B,49B,126B,79B,17B,126B,62B,-127B,0B,0B,0B,9B,13B,62B,29B,-56B,56B,-69B,72B,105B,-95B,100B,105B,116B,21B,-44B,86B,-5B,0B,0B,27B,-112B,0B,0B,0B,0B,0B,0B,0B,0B,0B,0B,0B,1B,75B,99B,82B,108B,-118B,-87B,-71B,14B,-97B,-92B,100B,-74B,-111B,106B,61B,-40B,0B,0B,0B,0B,0B,0B,0B,0B,0B,0B,0B,64B,-96B,0B,0B,0B,0B,0B,1B,63B,-128B,0B,0B,0B,0B,0B,0B,0B,0B,0B,0B,0B,0B,0B,0B,0B,0B,0B,0B,0B,0B,0B,0B,0B,0B,0B,0B,0B,0B,0B,0B,0B,0B,0B,0B,0B,0B,0B,0B,0B,0B,0B,0B,0B,0B,0B,0B,0B,0B,0B,0B,0B,0B,0B,0B,0B,0B,0B,0B,0B,0B,0B,0B,0B,0B,0B,0B,0B,0B,0B,0B,0B,0B,0B,0B,0B,0B,0B,0B,0B,0B,0B,0B,0B,0B,0B,0B,0B,0B,0B,0B,0B,0B,0B,0B,0B,0B,0B,0B,0B,0B,0B,0B,0B,0B,0B,0B,0B,0B,0B,0B,0B,0B,0B,0B,0B,0B,0B,0B,0B,0B,0B,0B,0B,0B,0B,0B,0B,0B,0B,0B,0B,0B,0B,0B,0B,0B,0B,0B,0B,0B,0B,0B,0B,0B,0B,0B,0B,0B,0B,0B,0B,0B,0B,0B,0B,0B,0B,0B,0B,0B,0B,0B,0B,0B,0B,0B,0B]}"}],"commandrewards":[]},{"uuid":"503079c8-2c3f-4951-af63-767092982afd","name":"Ninja","description":"ninja stays in the dark and swiftly kills his enemies.","x":142,"y":104,"icon":{"id":"littlelooter:katana"},"prerequisites":["e2d1d48e-bfa1-47d0-b196-bdc29db11d54"],"reward":[{"id":"minecraft:leather_boots","nbt":"{display:{color:1908001}}"},{"id":"minecraft:leather_leggings","nbt":"{display:{color:1908001}}"},{"id":"minecraft:leather_chestplate","nbt":"{display:{color:1908001}}"},{"id":"minecraft:leather_helmet","nbt":"{display:{color:1908001}}"},{"id":"littlelooter:katana"}],"commandrewards":[]},{"uuid":"a99d52d9-1a7c-48bf-8e53-8c4c4e89175d","name":"Archer","description":"The archer slays his foes from afar. His achery skills are worth more than gold.","x":57,"y":192,"icon":{"id":"minecraft:bow"},"prerequisites":["e2d1d48e-bfa1-47d0-b196-bdc29db11d54"],"reward":[{"id":"minecraft:bow"},{"id":"minecraft:arrow","amount":64},{"id":"harvestcraft:hardenedleatherhelmitem"},{"id":"harvestcraft:hardenedleatherchestitem"},{"id":"harvestcraft:hardenedleatherleggingsitem"},{"id":"harvestcraft:hardenedleatherbootsitem"}],"commandrewards":[]},{"uuid":"42d26513-56ec-4340-8dcc-c3f2a2bc07a7","name":"Gun Slinger","description":"The gun slinger is great with pistols and loves when its high noon.","x":96,"y":193,"icon":{"id":"mw:python"},"prerequisites":["e2d1d48e-bfa1-47d0-b196-bdc29db11d54"],"reward":[{"id":"mw:python"},{"id":"mw:bullet357","amount":64},{"id":"minecraft:leather_chestplate"},{"id":"comforts:sleeping_bag"}],"commandrewards":[]},{"uuid":"b810069b-1af2-41de-bcea-2b084d2b3604","name":"Radio man","description":"The radio man is just a coward and calls in for help whenever in need.","x":143,"y":133,"icon":{"id":"air_support:medical_crate_drop_remote"},"prerequisites":["e2d1d48e-bfa1-47d0-b196-bdc29db11d54"],"reward":[{"id":"air_support:crate_drop_remote","amount":2},{"id":"air_support:medical_crate_drop_remote","amount":2},{"id":"air_support:utility_crate_drop_remote","amount":2},{"id":"raiders:backup_transmitter","amount":2}],"commandrewards":[]},{"uuid":"a8f25ab0-5f32-4971-a7ab-5c40757fe96e","name":"Heavy","description":"The Heavy can tank all kinds of damage and keep on fighting.","x":136,"y":162,"icon":{"id":"minecraft:diamond_chestplate"},"prerequisites":["e2d1d48e-bfa1-47d0-b196-bdc29db11d54"],"reward":[{"id":"minecraft:chainmail_boots"},{"id":"minecraft:chainmail_chestplate"},{"id":"minecraft:chainmail_leggings"},{"id":"minecraft:chainmail_boots"},{"id":"littlelooter:nailed_bat"}],"commandrewards":[]},{"uuid":"e2d1d48e-bfa1-47d0-b196-bdc29db11d54","name":"Getting Started","description":"Welcome to the world! First you must choose your class. Remember you may only do this once so choose wisley!","x":16,"y":9,"icon":{"id":"minecraft:dirt"},"tasks":[{"type":"DETECT","description":"get some dirt!","longDescription":"Just get some dirt.","items":[{"item":{"id":"minecraft:dirt"}}]}],"reward":[{"id":"roughtweaks:medikit"}],"commandrewards":[]}],"reputationBar":[]}